{
    // WARNING! THIS IS ONE FILE LINKED (linked, not added) TO MULTIPLE PROJECTS.
    // Original file can be found inside 'Solution Items'

    "$schema": "https://raw.githubusercontent.com/DotNetAnalyzers/StyleCopAnalyzers/master/StyleCop.Analyzers/StyleCop.Analyzers/Settings/stylecop.schema.json",
    "settings": {
        "documentationRules": {
            "companyName": "Mateusz Soboń",
            "xmlHeader": false,

            "documentExposedElements": false,
            "documentInterfaces": false,
            "documentInternalElements": false,
            "documentPrivateElements": false,
            "documentPrivateFields": false,
            "fileNamingConvention": "stylecop",
            "excludeFromPunctuationCheck": [
                "summary",
                "example",
                "para",
                "c",
                "exception",
                "see",
                "seealso",
                "param",
                "typeparam",
                "paramref",
                "typeparamref",
                "list",
                "inheritdoc",
                "include"
            ]
        },

        "orderingRules": {
            "blankLinesBetweenUsingGroups": "omit",
            "usingDirectivesPlacement": "outsideNamespace",
            "elementOrder": [ "kind", "accessibility", "constant", "static", "readonly" ]
        },

        "maintainabilityRules": {
            "topLevelTypes": [ "class", "interface", "struct", "enum", "delegate" ]
        },

        "layoutRules": {
            "newlineAtEndOfFile": "allow",
            "allowConsecutiveUsings": true
        },

        "namingRules": {
            "allowedHungarianPrefixes": [ "db", "id" ]
        }
    }
}
